ldapmgk/__init__.py
ldapmgk/cli.py
ldapmgk/email.py
ldapmgk/utils.py
ldapmgk/commands/__init__.py
ldapmgk/commands/base.py
ldapmgk/commands/group.py
ldapmgk/commands/servergroup.py
ldapmgk/commands/user.py
ldapmgk-0.6.7.dist-info/DESCRIPTION.rst
ldapmgk-0.6.7.dist-info/LICENSE.txt
ldapmgk-0.6.7.dist-info/METADATA
ldapmgk-0.6.7.dist-info/RECORD
ldapmgk-0.6.7.dist-info/WHEEL
ldapmgk-0.6.7.dist-info/entry_points.txt
ldapmgk-0.6.7.dist-info/metadata.json
ldapmgk-0.6.7.dist-info/top_level.txt
