Metadata-Version: 2.0
Name: ldapmgk
Version: 0.6.7
Summary: Helper for managing an LDAP directory on CLI
Home-page: https://github.com/Movile/ldapmgk
Author: Hugo Cisneiros
Author-email: hugo.cisneiros@movile.com
License: GPLv3
Keywords: ldap,manager
Platform: UNKNOWN
Classifier: Intended Audience :: System Administrators
Classifier: Topic :: Utilities
Classifier: License :: OSI Approved :: GNU General Public License v3 (GPLv3)
Classifier: Natural Language :: English
Classifier: Operating System :: OS Independent
Classifier: Programming Language :: Python :: 2
Classifier: Programming Language :: Python :: 2.6
Classifier: Programming Language :: Python :: 2.7
Requires-Dist: Jinja2
Requires-Dist: certifi
Requires-Dist: docopt
Requires-Dist: python-ldap
Requires-Dist: requests
Provides-Extra: test
Requires-Dist: nose; extra == 'test'
